{
  "FAZ": [
    {
      "box_2d": [
        0.397,
        0.441,
        0.604,
        0.631
      ]
    }
  ],
  "vessel_dropout": [
    {
      "box_2d": [
        0.331,
        0.381,
        0.469,
        0.481
      ]
    },
    {
      "box_2d": [
        0.604,
        0.481,
        0.719,
        0.619
      ]
    }
  ],
  "capillary_non-perfusion": [
    {
      "box_2d": [
        0.322,
        0.146,
        0.793,
        0.431
      ]
    },
    {
      "box_2d": [
        0.131,
        0.441,
        0.397,
        0.681
      ]
    },
    {
      "box_2d": [
        0.403,
        0.638,
        0.793,
        0.888
      ]
    }
  ]
}