[
  {
    "box_2d": [
      0.604,
      0.363,
      0.791,
      0.641
    ],
    "label": "Optic Disc"
  },
  {
    "box_2d": [
      0.198,
      0.395,
      0.245,
      0.435
    ],
    "label": "Exudates"
  },
  {
    "box_2d": [
      0.345,
      0.245,
      0.368,
      0.265
    ],
    "label": "Exudates"
  },
  {
    "box_2d": [
      0.221,
      0.458,
      0.248,
      0.481
    ],
    "label": "Hemorrhages"
  },
  {
    "box_2d": [
      0.165,
      0.695,
      0.18,
      0.71
    ],
    "label": "Microaneurysms"
  },
  {
    "box_2d": [
      0.185,
      0.755,
      0.2,
      0.77
    ],
    "label": "Microaneurysms"
  },
  {
    "box_2d": [
      0.265,
      0.335,
      0.28,
      0.35
    ],
    "label": "Microaneurysms"
  }
]