[
  {
    "box_2d": [
      0.785,
      0.415,
      0.915,
      0.585
    ],
    "label": "Optic Disc"
  },
  {
    "box_2d": [
      0.418,
      0.321,
      0.542,
      0.431
    ],
    "label": "Exudates"
  },
  {
    "box_2d": [
      0.388,
      0.562,
      0.485,
      0.645
    ],
    "label": "Exudates"
  },
  {
    "box_2d": [
      0.341,
      0.681,
      0.382,
      0.722
    ],
    "label": "Exudates"
  },
  {
    "box_2d": [
      0.495,
      0.485,
      0.536,
      0.526
    ],
    "label": "Exudates"
  },
  {
    "box_2d": [
      0.462,
      0.212,
      0.495,
      0.245
    ],
    "label": "Hemorrhages"
  },
  {
    "box_2d": [
      0.515,
      0.245,
      0.548,
      0.278
    ],
    "label": "Hemorrhages"
  },
  {
    "box_2d": [
      0.385,
      0.285,
      0.405,
      0.305
    ],
    "label": "Microaneurysms"
  },
  {
    "box_2d": [
      0.345,
      0.455,
      0.365,
      0.475
    ],
    "label": "Microaneurysms"
  }
]